{
    "sourceFile": "#sourse/scss/post.scss",
    "activeCommit": 0,
    "commits": [
        {
            "activePatchIndex": 0,
            "patches": [
                {
                    "date": 1724234592610,
                    "content": "Index: \n===================================================================\n--- \n+++ \n"
                }
            ],
            "date": 1724234592610,
            "name": "Commit-0",
            "content": ".postwrapper {\r\n    // padding: 96px 0 0 0;\r\n    background: #fff;\r\n    font-family: \"Montserrat\", sans-serif;\r\n}\r\n\r\n.postcontent {\r\n    padding: 147px 0 85px 0;\r\n    position: relative;\r\n\r\n    &::after {\r\n        content: '';\r\n        display: block;\r\n        background: linear-gradient(125.34deg, #CDFF7C 14.35%, #8CFFAC 54.63%, #93FFEB 101.27%);\r\n        height: 2px;\r\n        width: 100%;\r\n        position: absolute;\r\n        left: 0;\r\n        bottom: 0;\r\n    }\r\n}\r\n\r\n.postcontainer {\r\n    max-width: 1492px;\r\n    margin: 0 auto;\r\n}\r\n\r\n.postmiansect {\r\n    display: flex;\r\n    padding-bottom: 150px;\r\n}\r\n\r\n.postmiansect__descr {\r\n    width: 100%;\r\n    max-width: 50%;\r\n    flex: 0 0 50%;\r\n    padding-right: 17px;\r\n\r\n    h1 {\r\n        color: #000;\r\n        letter-spacing: 0.01em;\r\n        font-weight: 700;\r\n        font-size: 64px;\r\n        line-height: 110%;\r\n        margin-bottom: 50px;\r\n    }\r\n}\r\n\r\n.postmiansect__img {\r\n    width: 100%;\r\n    max-width: 50%;\r\n    flex: 0 0 50%;\r\n\r\n    img {\r\n        width: 100%;\r\n    }\r\n}\r\n\r\n.postmiansect__tags {\r\n    margin-bottom: 50px;\r\n\r\n    a {\r\n        display: inline-block;\r\n        margin-right: 29px;\r\n        color: #BEBEBE;\r\n        font-weight: 400;\r\n        font-size: 14px;\r\n        line-height: 130%;\r\n\r\n\r\n        &:last-child {\r\n            margin-right: 0;\r\n        }\r\n    }\r\n}\r\n\r\n.postauthor {\r\n    display: flex;\r\n    align-items: center;\r\n\r\n    .postauthor__img {\r\n        width: 100%;\r\n        max-width: 49px;\r\n        flex: 0 0 49px;\r\n\r\n        .imgwrap {\r\n            width: 100%;\r\n            height: 49px;\r\n            border-radius: 50%;\r\n            overflow: hidden;\r\n\r\n            img {\r\n                width: 100%;\r\n                height: 100%;\r\n                object-fit: cover;\r\n                object-position: 50% 50%;\r\n            }\r\n        }\r\n    }\r\n\r\n    .postauthor__descr {\r\n        width: 100%;\r\n        max-width: calc(100% - 49px);\r\n        flex: 0 0 calc(100% - 49px);\r\n        padding-left: 13px;\r\n\r\n        .name {\r\n            color: #000;\r\n            letter-spacing: 0.05em;\r\n            font-size: 16px;\r\n            line-height: 150%;\r\n            margin: 0 0 8px 0;\r\n\r\n            a {\r\n                color: #000;\r\n                text-decoration: underline;\r\n                letter-spacing: 0.05em;\r\n                font-weight: 700;\r\n            }\r\n        }\r\n\r\n        .date {\r\n            margin: 0;\r\n            color: #000;\r\n            letter-spacing: 0.05em;\r\n            font-size: 12px;\r\n            line-height: 150%;\r\n\r\n            span {\r\n                font-weight: 600;\r\n            }\r\n        }\r\n    }\r\n}\r\n\r\n.postmiansectbody {\r\n    display: flex;\r\n\r\n    .postmiansectbody__leftbar {\r\n        width: 100%;\r\n        max-width: 480px;\r\n        flex: 0 0 480px;\r\n    }\r\n\r\n    .postmiansectbody__post {\r\n        width: 100%;\r\n        max-width: calc(100% - 760px);\r\n        flex: 0 0 calc(100% - 760px);\r\n    }\r\n\r\n    .postmiansectbody__rightbar {\r\n        width: 100%;\r\n        max-width: 280px;\r\n        flex: 0 0 280px;\r\n    }\r\n}\r\n\r\n.postmiansectbody__post {\r\n    padding-bottom: 20px;\r\n\r\n    h2,\r\n    h3,\r\n    h4,\r\n    h5,\r\n    h6 {\r\n        color: #000000;\r\n        opacity: 0.8;\r\n    }\r\n\r\n    &>p {\r\n        color: #333333;\r\n        font-weight: 400;\r\n        font-size: 16px;\r\n        line-height: 150%;\r\n        margin-bottom: 30px;\r\n    }\r\n\r\n    h2 {\r\n        margin: 50px 0 60px;\r\n        position: relative;\r\n    }\r\n\r\n    .postgetconsultation {\r\n        margin-bottom: 30px;\r\n    }\r\n\r\n    &>ul {\r\n        padding-left: 17px;\r\n        margin-bottom: 30px;\r\n\r\n        li {\r\n            display: block;\r\n            position: relative;\r\n            padding-left: 16px;\r\n            color: #000000;\r\n            opacity: 0.8;\r\n            font-weight: 400;\r\n            font-size: 16px;\r\n            line-height: 150%;\r\n            margin-bottom: 8px;\r\n\r\n            &:last-child {\r\n                margin-bottom: 0;\r\n            }\r\n\r\n            &::before {\r\n                content: '';\r\n                display: inline-block;\r\n                width: 7px;\r\n                height: 7px;\r\n                border-radius: 50%;\r\n                background: linear-gradient(125.34deg, #CDFF7C 14.35%, #8CFFAC 54.63%, #93FFEB 101.27%);\r\n                position: absolute;\r\n                left: 0;\r\n                top: 9px;\r\n            }\r\n        }\r\n    }\r\n\r\n    &>ol {\r\n        li {\r\n            padding-left: 8px;\r\n            position: relative;\r\n            color: #000000;\r\n            opacity: 0.8;\r\n            font-weight: 400;\r\n            font-size: 16px;\r\n            line-height: 150%;\r\n            margin-bottom: 8px;\r\n\r\n            &:last-child {\r\n                margin-bottom: 0;\r\n            }\r\n        }\r\n    }\r\n\r\n    blockquote {\r\n        margin: 50px 0 60px;\r\n        position: relative;\r\n        font-weight: 800;\r\n        font-size: 36px;\r\n        line-height: 130%;\r\n        color: #000000;\r\n        opacity: 0.8;\r\n\r\n        &::after {\r\n            content: \"\";\r\n            z-index: -1;\r\n            display: block;\r\n            position: absolute;\r\n            left: -28px;\r\n            top: 0;\r\n            width: 60%;\r\n            height: calc(100% + 13px);\r\n            border: 2px solid;\r\n            border-image-slice: 1;\r\n            border-width: 2px;\r\n            border-image-source: linear-gradient(125.34deg, #CDFF7C 14.35%, #8CFFAC 54.63%, #93FFEB 101.27%);\r\n            border-top: none;\r\n            border-right: none;\r\n        }\r\n    }\r\n\r\n}\r\n\r\n.postgetconsultation {\r\n    padding: 22px 55px;\r\n    display: flex;\r\n    align-items: center;\r\n    background: rgba(15, 15, 16, 0.9);\r\n    box-shadow: 0px 4px 11px rgba(0, 0, 0, 0.15);\r\n\r\n    p {\r\n        width: 100%;\r\n        max-width: calc(100% - 268px);\r\n        flex: 0 0 calc(100% - 268px);\r\n        margin: 0;\r\n        color: #fff;\r\n        font-weight: 700;\r\n        font-size: 22px;\r\n        line-height: 140%;\r\n        padding-right: 49px;\r\n    }\r\n\r\n    a {\r\n        width: 100%;\r\n        max-width: 268px;\r\n        flex: 0 0 268px;\r\n        height: 67px;\r\n        display: flex;\r\n        align-items: center;\r\n        justify-content: center;\r\n        background: linear-gradient(125.34deg, #CDFF7C 14.35%, #8CFFAC 54.63%, #93FFEB 101.27%);\r\n        letter-spacing: 0.02em;\r\n        color: #0F0F10;\r\n        font-weight: 700;\r\n        font-size: 18px;\r\n        line-height: 130%;\r\n        transition: 0.3s;\r\n\r\n        &:hover {\r\n            filter: hue-rotate(40deg);\r\n            box-shadow: 0 8px 10px #000;\r\n        }\r\n    }\r\n}\r\n\r\n.postauthorinfo {\r\n    margin-top: 75px;\r\n    display: flex;\r\n    justify-content: space-between;\r\n}\r\n\r\n.postauthorinfo__author {\r\n    display: flex;\r\n\r\n    .postauthorinfo__author-img {\r\n        width: 100%;\r\n        max-width: 90px;\r\n        flex: 0 0 90px;\r\n\r\n        .imgwrap {\r\n            width: 100%;\r\n            height: 90px;\r\n            overflow: hidden;\r\n            border-radius: 50%;\r\n\r\n            img {\r\n                width: 100%;\r\n                height: 100%;\r\n                object-fit: cover;\r\n                object-position: 50% 50%;\r\n            }\r\n        }\r\n    }\r\n\r\n    .postauthorinfo__author-descr {\r\n        width: 100%;\r\n        max-width: calc(100% - 90px);\r\n        flex: 0 0 calc(100% - 90px);\r\n        padding-left: 22px;\r\n\r\n        .name {\r\n            color: #000000;\r\n            opacity: 0.8;\r\n            letter-spacing: 0.05em;\r\n            text-transform: uppercase;\r\n            font-size: 16px;\r\n            line-height: 150%;\r\n            margin-bottom: 3px;\r\n\r\n            a {\r\n                font-weight: 700;\r\n                text-decoration: underline;\r\n                color: #000000;\r\n            }\r\n        }\r\n\r\n        .job {\r\n            margin-bottom: 20px;\r\n            color: rgba(0, 0, 0, 0.6);\r\n            opacity: 0.8;\r\n            font-weight: 600;\r\n            font-size: 14px;\r\n            line-height: 150%;\r\n        }\r\n\r\n        .date {\r\n            letter-spacing: 0.05em;\r\n            color: #000000;\r\n            font-size: 12px;\r\n            line-height: 150%;\r\n            margin: 0;\r\n        }\r\n    }\r\n}\r\n\r\n.postauthorinfo__socials {\r\n    width: 181px;\r\n    text-align: center;\r\n\r\n    p {\r\n        margin-bottom: 16px;\r\n        color: #000;\r\n        letter-spacing: 0.02em;\r\n        font-weight: 600;\r\n        font-size: 20px;\r\n        line-height: 130%;\r\n    }\r\n\r\n    ul {\r\n        list-style-type: none;\r\n        padding: 0;\r\n        margin: 0;\r\n\r\n        li {\r\n            display: inline-block;\r\n            vertical-align: middle;\r\n            margin-right: 11px;\r\n\r\n            &:last-child {\r\n                margin-right: 0;\r\n            }\r\n        }\r\n    }\r\n}\r\n\r\n.postmiansectbody__leftbar {\r\n    .blogsocials {\r\n        position: relative;\r\n        left: initial;\r\n        top: initial;\r\n\r\n        ul {\r\n            top: 160px;\r\n        }\r\n    }\r\n}\r\n\r\n.postmiansectbody__rightbar {\r\n    text-align: right;\r\n}\r\n\r\n.stickysect {\r\n    position: sticky;\r\n    top: 160px;\r\n}\r\n\r\n.sbbox {\r\n    width: 252px;\r\n    display: inline-block;\r\n    background: #F1F1F1;\r\n    padding: 24px;\r\n    text-align: left;\r\n\r\n\r\n    p {\r\n        color: #000;\r\n        font-weight: 700;\r\n        font-size: 18px;\r\n        line-height: 150%;\r\n        margin-bottom: 48px;\r\n    }\r\n\r\n    a {\r\n        width: 100%;\r\n        min-height: 52px;\r\n        background: linear-gradient(125.34deg, #CDFF7C 14.35%, #8CFFAC 54.63%, #93FFEB 101.27%);\r\n        color: #0F0F10;\r\n        letter-spacing: 0.281px;\r\n        font-weight: 700;\r\n        font-size: 14.04px;\r\n        line-height: 130%;\r\n        display: flex;\r\n        align-items: center;\r\n        justify-content: center;\r\n        transition: 0.3s;\r\n        text-align: center;\r\n        padding: 5px 10px;\r\n\r\n        &:hover {\r\n            filter: hue-rotate(40deg);\r\n        }\r\n    }\r\n}\r\n\r\n.alsolike {\r\n    padding: 100px 0 100px;\r\n\r\n    h2 {\r\n        margin-bottom: 48px;\r\n        font-weight: 700;\r\n        font-size: 56px;\r\n        line-height: 130%;\r\n        color: #000;\r\n    }\r\n\r\n    .postbox {\r\n        border: 1px solid;\r\n        border-image-slice: 1;\r\n        border-width: 1px;\r\n        border-image-source: linear-gradient(125.34deg, #CDFF7C 14.35%, #8CFFAC 54.63%, #93FFEB 101.27%);\r\n    }\r\n\r\n    .blog__body {\r\n        padding-bottom: 0;\r\n    }\r\n}\r\n\r\n.postreadreview {\r\n    padding: 130px 0;\r\n    background-color: #1B1B1C;\r\n    position: relative;\r\n\r\n    &::after {\r\n        content: '';\r\n        display: block;\r\n        position: absolute;\r\n        left: 0;\r\n        top: 0;\r\n        width: 100%;\r\n        height: 100%;\r\n        background: url('../images/new/grid.png') no-repeat 0 0 / 100%;\r\n    }\r\n\r\n    &::before {\r\n        content: '';\r\n        display: block;\r\n        position: absolute;\r\n        right: 100px;\r\n        top: 70px;\r\n        background-image: url('../images/new/reviewpic.png');\r\n        background-repeat: no-repeat;\r\n        background-position: 0 0;\r\n        width: 650px;\r\n        height: 560px;\r\n        z-index: 2;\r\n    }\r\n\r\n    .container__small {\r\n        position: relative;\r\n        z-index: 2;\r\n    }\r\n\r\n    h2 {\r\n        margin-bottom: 48px;\r\n        color: #fff;\r\n        font-weight: 700;\r\n        font-size: 72px;\r\n        line-height: 120%;\r\n    }\r\n\r\n    .descr {\r\n        margin-bottom: 65px;\r\n        max-width: 750px;\r\n\r\n        p {\r\n            font-size: 24px;\r\n            line-height: 175%;\r\n            color: #fff;\r\n\r\n            &:last-child {\r\n                margin-bottom: 0;\r\n            }\r\n        }\r\n    }\r\n\r\n    .postreadreview__link {\r\n        max-width: 318px;\r\n        width: 100%;\r\n        height: 67px;\r\n        display: flex;\r\n        align-items: center;\r\n        justify-content: center;\r\n        color: #0F0F10;\r\n        letter-spacing: 0.02em;\r\n        font-weight: 700;\r\n        font-size: 18px;\r\n        line-height: 130%;\r\n        background: linear-gradient(125.34deg, #CDFF7C 14.35%, #8CFFAC 54.63%, #93FFEB 101.27%);\r\n        transition: 0.3s;\r\n\r\n        &:hover {\r\n            filter: hue-rotate(40deg);\r\n        }\r\n    }\r\n}\r\n\r\n.tabletsocials {\r\n    display: none;\r\n}\r\n\r\n\r\n.progress-container {\r\n    width: 100%;\r\n    height: 1px;\r\n    background: rgba(201, 250, 61, 0.29);\r\n    position: fixed;\r\n    top: 96px;\r\n    z-index: 13;\r\n\r\n}\r\n\r\n.progress-bar {\r\n    height: 3px;\r\n    background: linear-gradient(125.34deg, #CDFF7C 14.35%, #8CFFAC 54.63%, #93FFEB 101.27%);\r\n    width: 0%;\r\n}\r\n\r\n\r\n\r\n@media(max-width:1800.8px) {\r\n    .postreadreview {\r\n        &::before {\r\n            right: 25px;\r\n            top: 70px;\r\n        }\r\n    }\r\n\r\n}\r\n\r\n@media(max-width:1600.8px) {\r\n\r\n    .postcontainer {\r\n        max-width: 1268px;\r\n    }\r\n\r\n    .postcontent {\r\n        padding: 100px 0 50px;\r\n    }\r\n\r\n    .postmiansect__descr h1 {\r\n        font-size: 52px;\r\n    }\r\n\r\n    .postmiansectbody .postmiansectbody__leftbar {\r\n        max-width: 420px;\r\n        flex: 0 0 420px;\r\n    }\r\n\r\n    .postmiansectbody .postmiansectbody__post {\r\n        max-width: calc(100% - 700px);\r\n        flex: 0 0 calc(100% - 700px);\r\n    }\r\n\r\n    .alsolike h2 {\r\n        font-size: 46px;\r\n    }\r\n\r\n    .alsolike {\r\n        padding: 80px 0;\r\n    }\r\n\r\n    .postreadreview h2 {\r\n        font-size: 52px;\r\n    }\r\n\r\n    .postreadreview .descr p {\r\n        font-size: 21px;\r\n    }\r\n\r\n    .postreadreview .descr {\r\n        max-width: 650px;\r\n    }\r\n\r\n    .postreadreview {\r\n        padding: 100px 0;\r\n    }\r\n\r\n    .postreadreview {\r\n        &::before {\r\n            background-size: 100%;\r\n            width: 550px;\r\n            height: 460px;\r\n        }\r\n    }\r\n\r\n    .postreadreview:after {\r\n        background-size: cover;\r\n    }\r\n\r\n    .postreadreview .descr {\r\n        max-width: 600px;\r\n    }\r\n}\r\n\r\n@media(max-width:1440.8px) {\r\n    .postmiansectbody .postmiansectbody__leftbar {\r\n        max-width: 320px;\r\n        flex: 0 0 320px;\r\n    }\r\n\r\n    .postmiansectbody .postmiansectbody__post {\r\n        max-width: calc(100% - 600px);\r\n        flex: 0 0 calc(100% - 600px);\r\n    }\r\n\r\n}\r\n\r\n@media(max-width:1400.8px) {\r\n    .postcontainer {\r\n        max-width: 1000px;\r\n    }\r\n\r\n    .postmiansect__descr h1 {\r\n        font-size: 42px;\r\n        margin-bottom: 30px;\r\n    }\r\n\r\n    .postmiansect__tags {\r\n        margin-bottom: 30px;\r\n    }\r\n\r\n    .postmiansect {\r\n        padding-bottom: 80px;\r\n    }\r\n\r\n    .postmiansectbody .postmiansectbody__leftbar {\r\n        max-width: 300px;\r\n        flex: 0 0 300px;\r\n    }\r\n\r\n    .postmiansectbody .postmiansectbody__rightbar {\r\n        max-width: 200px;\r\n        flex: 0 0 200px;\r\n    }\r\n\r\n    .postmiansectbody .postmiansectbody__post {\r\n        max-width: calc(100% - 500px);\r\n        flex: 0 0 calc(100% - 500px);\r\n    }\r\n\r\n    .sbbox {\r\n        width: 180px;\r\n\r\n        p {\r\n            font-size: 16px;\r\n        }\r\n\r\n        a {\r\n            max-width: 100%;\r\n        }\r\n    }\r\n\r\n    .postmiansectbody__post h2 {\r\n        font-size: 32px;\r\n    }\r\n\r\n    .postmiansectbody__post blockquote {\r\n        font-size: 32px;\r\n    }\r\n\r\n    .postmiansectbody__post h3 {\r\n        font-size: 30px;\r\n    }\r\n\r\n    .postgetconsultation {\r\n        flex-wrap: wrap;\r\n\r\n        p {\r\n            max-width: 100%;\r\n            flex: 0 0 100%;\r\n            margin-bottom: 15px;\r\n            padding-right: 0;\r\n        }\r\n\r\n    }\r\n\r\n    .alsolike h2 {\r\n        font-size: 36px;\r\n        margin-bottom: 30px;\r\n    }\r\n\r\n    .alsolike {\r\n        padding-bottom: 60px;\r\n    }\r\n\r\n    .postreadreview:before {\r\n        background-size: 100%;\r\n        width: 400px;\r\n        height: 340px;\r\n    }\r\n\r\n    .postreadreview h2 {\r\n        font-size: 42px;\r\n        margin-bottom: 20px;\r\n    }\r\n\r\n    .postreadreview .descr p {\r\n        font-size: 18px;\r\n    }\r\n\r\n    .postreadreview .descr {\r\n        margin-bottom: 20px;\r\n    }\r\n\r\n    .postnav {\r\n        padding-left: 30px;\r\n    }\r\n\r\n\r\n\r\n\r\n\r\n}\r\n\r\n@media(max-width:1199.8px) {\r\n    .postcontainer {\r\n        max-width: calc(100% - 120px);\r\n    }\r\n\r\n    .postmiansectbody__rightbar {\r\n        display: none;\r\n    }\r\n\r\n\r\n    .postmiansectbody .postmiansectbody__leftbar {\r\n        max-width: 100px;\r\n        flex: 0 0 100px;\r\n    }\r\n\r\n    .postmiansectbody__leftbar .blogsocials {\r\n        text-align: left;\r\n    }\r\n\r\n    .postmiansectbody .postmiansectbody__post {\r\n        max-width: calc(100% - 100px);\r\n        flex: 0 0 calc(100% - 100px);\r\n    }\r\n\r\n    .postreadreview .descr {\r\n        max-width: 500px;\r\n    }\r\n\r\n    .postmiansectbody__leftbar {\r\n        display: none;\r\n    }\r\n\r\n    .tabletsocials {\r\n        display: block;\r\n    }\r\n\r\n    .postmiansectbody .postmiansectbody__post {\r\n        max-width: 100%;\r\n        flex: 0 0 100%;\r\n    }\r\n\r\n\r\n    .articlecontainer {\r\n        padding-right: 0 !important;\r\n        max-width: calc(100% - 120px);\r\n        margin: 0 auto;\r\n    }\r\n\r\n    .tabletsocials {\r\n        display: flex;\r\n        flex-wrap: wrap;\r\n        padding-top: 30px;\r\n    }\r\n\r\n    .mobsocbox {\r\n        width: 100%;\r\n        max-width: 50%;\r\n        flex: 0 0 50%;\r\n\r\n        p {\r\n            color: #4B4B4B;\r\n            font-size: 16px;\r\n            font-weight: 500;\r\n            line-height: 130%;\r\n            margin-bottom: 10px;\r\n        }\r\n\r\n        ul {\r\n            list-style-type: none;\r\n            padding: 0;\r\n            margin: 0;\r\n\r\n            li {\r\n                display: inline-flex;\r\n                align-items: center;\r\n                justify-content: center;\r\n                width: 56px;\r\n                height: 56px;\r\n                background: linear-gradient(125.34deg, #CDFF7C 14.35%, #8CFFAC 54.63%, #93FFEB 101.27%);\r\n                border-radius: 50%;\r\n                margin-bottom: 15px;\r\n                vertical-align: middle;\r\n                margin-right: 10px;\r\n\r\n                a {\r\n                    text-decoration: none;\r\n                    width: 52px;\r\n                    height: 52px;\r\n                    background: #fff;\r\n                    display: inline-flex;\r\n                    align-items: center;\r\n                    justify-content: center;\r\n                    border-radius: 50%;\r\n                    -webkit-transition: 0.1s;\r\n                    transition: 0.1s;\r\n\r\n                    img {\r\n                        max-width: 100%;\r\n                    }\r\n                }\r\n            }\r\n        }\r\n    }\r\n\r\n}\r\n\r\n@media(max-width:991.8px) {\r\n\r\n    .postmiansect {\r\n        flex-wrap: wrap;\r\n    }\r\n\r\n    .postmiansect__descr,\r\n    .postmiansect__img {\r\n        max-width: 100%;\r\n        flex: 0 0 100%;\r\n    }\r\n\r\n    .postmiansect__tags {\r\n        display: none;\r\n    }\r\n\r\n    .postcontent {\r\n        padding: 70px 0 50px;\r\n    }\r\n\r\n    .postmiansect__descr {\r\n        margin-bottom: 30px;\r\n    }\r\n\r\n    .postmiansectbody__leftbar {\r\n        display: none;\r\n    }\r\n\r\n    .postmiansectbody .postmiansectbody__post {\r\n        max-width: 100%;\r\n        flex: 0 0 100%;\r\n    }\r\n\r\n    .postreadreview:before {\r\n        width: 100px;\r\n        height: 100px;\r\n        background-image: url(../images/new/subscribe-pic.png);\r\n        background-size: contain;\r\n        top: 100px;\r\n    }\r\n\r\n    .tabletsocials {\r\n        max-width: 500px;\r\n    }\r\n\r\n\r\n\r\n}\r\n\r\n@media(max-width:767.8px) {\r\n    .postreadreview h2 {\r\n        font-size: 30px;\r\n        padding-right: 50px;\r\n    }\r\n\r\n    .postreadreview {\r\n        padding: 70px 0;\r\n    }\r\n\r\n    .postreadreview:before {\r\n        top: 50px;\r\n    }\r\n\r\n    .progress-container {\r\n        top: 96px;\r\n    }\r\n}\r\n\r\n@media(max-width:575.8px) {\r\n    .postcontent {\r\n        padding: 40px 0 24px;\r\n    }\r\n\r\n    .postcontainer {\r\n        max-width: 100%;\r\n        padding-left: 19px;\r\n        padding-right: 19px;\r\n    }\r\n\r\n    .postmiansect__descr h1 {\r\n        text-align: center;\r\n        font-size: 32px;\r\n        line-height: 120%;\r\n        margin-bottom: 40px;\r\n    }\r\n\r\n    .postauthor {\r\n        margin: 0 auto;\r\n        max-width: 240px;\r\n    }\r\n\r\n    .postauthor .postauthor__descr .date {\r\n        letter-spacing: normal;\r\n    }\r\n\r\n    .tabletsocials {\r\n        text-align: center;\r\n\r\n        li {\r\n            width: 42px;\r\n            height: 42px;\r\n            margin-bottom: 0;\r\n\r\n            &:last-child {\r\n                margin-right: 0;\r\n            }\r\n\r\n            a {\r\n                width: 40px;\r\n                height: 40px;\r\n\r\n                img {\r\n                    transform: scale(0.8);\r\n                }\r\n            }\r\n        }\r\n    }\r\n\r\n    .postmiansect {\r\n        padding-bottom: 24px;\r\n    }\r\n\r\n    .postmiansectbody__post h5,\r\n    .postmiansectbody__post h6 {\r\n        font-size: 16px;\r\n    }\r\n\r\n    .postmiansectbody__post>p {\r\n        line-height: 160%;\r\n    }\r\n\r\n    .postmiansectbody__post h2 {\r\n        padding-left: 0px;\r\n        font-size: 36px;\r\n        line-height: 130%\r\n    }\r\n\r\n    .postmiansectbody__post blockquote {\r\n        padding-left: 28px;\r\n        font-size: 28px;\r\n        line-height: 130%\r\n    }\r\n\r\n    .postmiansectbody__post blockquote:after {\r\n        left: 0;\r\n        top: 0;\r\n        width: 100%;\r\n    }\r\n\r\n    .postmiansectbody__post .postgetconsultation {\r\n        padding: 30px 20px;\r\n        display: block;\r\n\r\n        p {\r\n            font-size: 22px;\r\n            line-height: 140%;\r\n        }\r\n\r\n        a {\r\n            max-width: 320px;\r\n            margin: 0 auto;\r\n            width: 100%;\r\n            flex: initial;\r\n        }\r\n    }\r\n\r\n    .postmiansectbody__post>ul {\r\n        padding-left: 0;\r\n    }\r\n\r\n    .postmiansectbody__post>ol {\r\n        padding-left: 20px;\r\n    }\r\n\r\n    .postauthorinfo {\r\n        margin-top: 48px;\r\n        flex-wrap: wrap;\r\n    }\r\n\r\n    .postauthorinfo__author,\r\n    .postauthorinfo__socials {\r\n        max-width: 100%;\r\n        flex: 0 0 100%;\r\n    }\r\n\r\n    .postauthorinfo__author .postauthorinfo__author-img {\r\n        max-width: 50px;\r\n        flex: 0 0 50px;\r\n\r\n        .imgwrap {\r\n            height: 50px;\r\n        }\r\n    }\r\n\r\n    .postauthorinfo__author .postauthorinfo__author-descr {\r\n        max-width: calc(100% - 50px);\r\n        flex: 0 0 calc(100% - 50px);\r\n        padding-left: 13px;\r\n    }\r\n\r\n    .postauthorinfo__author .postauthorinfo__author-descr .job {\r\n        display: none;\r\n    }\r\n\r\n    .postauthorinfo__author .postauthorinfo__author-descr .name {\r\n        text-transform: initial;\r\n    }\r\n\r\n    .postauthorinfo__author {\r\n        max-width: 240px;\r\n        margin: 0 auto 40px;\r\n    }\r\n\r\n    .postauthorinfo__socials p {\r\n        margin-bottom: 16px;\r\n        font-size: 20px;\r\n        line-height: 130%;\r\n    }\r\n\r\n    .alsolike {\r\n        padding: 40px 0 0 0;\r\n    }\r\n\r\n    .alsolike h2 {\r\n        margin-bottom: 48px;\r\n        font-size: 32px;\r\n        line-height: 130%;\r\n        text-align: center;\r\n    }\r\n\r\n    .postreadreview .descr {\r\n        display: none;\r\n    }\r\n\r\n    .postreadreview {\r\n        padding: 30px;\r\n\r\n        .container__small {\r\n            padding: 0;\r\n        }\r\n    }\r\n\r\n    .postreadreview h2 {\r\n        br {\r\n            display: none;\r\n        }\r\n\r\n        font-size: 22px;\r\n        line-height: 140%;\r\n        max-width: 200px;\r\n        padding-left: 23px;\r\n        padding-right: 0;\r\n    }\r\n\r\n    .postreadreview:after {\r\n        display: none;\r\n    }\r\n\r\n\r\n    .progress-container {\r\n        top: 80px;\r\n    }\r\n\r\n    .progress-container {\r\n        top: 96px;\r\n    }\r\n\r\n}\r\n\r\n\r\n// Blog helpers\r\n\r\n.postmiansectbody__post h1 {\r\n    color: #000000;\r\n    font-weight: 700;\r\n    font-size: 80px;\r\n    line-height: 120%;\r\n}\r\n\r\n.postmiansectbody__post h2 {\r\n    letter-spacing: 0.01em;\r\n    color: #000000;\r\n    font-weight: 700;\r\n    font-size: 52px;\r\n    line-height: 110%;\r\n    margin-bottom: 30px;\r\n}\r\n\r\n.postmiansectbody__post h3 {\r\n    font-weight: 700;\r\n    font-size: 36px;\r\n    line-height: 120%;\r\n    color: #000000;\r\n    margin-bottom: 30px;\r\n}\r\n\r\n.postmiansectbody__post h4 {\r\n    color: #000000;\r\n    opacity: 0.8;\r\n    font-weight: 800;\r\n    font-size: 24px;\r\n    line-height: 130%;\r\n    margin-bottom: 20px;\r\n}\r\n\r\n.postmiansectbody__post h5 {\r\n    font-weight: 700;\r\n    font-size: 21px;\r\n    line-height: 135%;\r\n    color: #000000;\r\n    opacity: 0.8;\r\n    margin-bottom: 20px;\r\n}\r\n\r\n.postmiansectbody__post h6 {\r\n    font-weight: 700;\r\n    font-size: 18px;\r\n    line-height: 130%;\r\n    color: #000000;\r\n    opacity: 0.8;\r\n    margin-bottom: 20px;\r\n}\r\n\r\n.postmiansectbody__post>ol {\r\n    list-style: none;\r\n    counter-reset: my-awesome-counter;\r\n    padding-left: 10px;\r\n    margin-bottom: 30px;\r\n\r\n    li {\r\n        counter-increment: my-awesome-counter;\r\n    }\r\n\r\n    li::before {\r\n        content: counter(my-awesome-counter) \". \";\r\n        font-weight: bold;\r\n    }\r\n}\r\n\r\n.posttablewrapper {\r\n    width: 100%;\r\n    overflow: hidden;\r\n\r\n    table {\r\n        border-spacing: 10px;\r\n        border-collapse: separate;\r\n\r\n        th,\r\n        td {\r\n            padding: 12px 17px;\r\n            background: #F6F6F6;\r\n            font-weight: 400;\r\n            font-size: 16px;\r\n            line-height: 150%;\r\n            color: #000000;\r\n        }\r\n    }\r\n}\r\n\r\n.postmiansectbody__post>p a {\r\n    color: #3663D8;\r\n    text-decoration: underline;\r\n\r\n    &:hover {\r\n        text-decoration: none;\r\n    }\r\n}\r\n\r\n.codeexample {\r\n    padding: 12px;\r\n    background: #F6F6F6;\r\n    display: inline-block;\r\n    margin-bottom: 30px;\r\n    font-weight: 400;\r\n    font-size: 16px;\r\n    line-height: 150%;\r\n    color: #000000;\r\n}\r\n\r\n.progress-container {\r\n    transition: 0.3s;\r\n    -webkit-transition: 0.3s;\r\n    -moz-transition: 0.3s;\r\n    -ms-transition: 0.3s;\r\n    -o-transition: 0.3s;\r\n}\r\n\r\n.progress-container.support {\r\n    top: 136px;\r\n}\r\n\r\n.postmiansectbody__post img {\r\n    max-width: 100%;\r\n    height: auto;\r\n}\r\n\r\n\r\n@media(max-width:991.8px) {\r\n    .postmiansectbody__post h1 {\r\n        font-size: 42px;\r\n    }\r\n\r\n    .postmiansectbody__post h2 {\r\n        font-size: 32px;\r\n    }\r\n\r\n    .postmiansectbody__post h3 {\r\n        font-size: 30px;\r\n    }\r\n\r\n    .postmiansectbody__post h4 {\r\n        font-size: 24px;\r\n    }\r\n\r\n}\r\n\r\n@media(max-width:767.8px) {\r\n    .posttablewrapper {\r\n        overflow: scroll;\r\n\r\n        table {\r\n            width: 800px;\r\n        }\r\n    }\r\n\r\n    .codeexample {\r\n        display: block;\r\n        overflow: auto;\r\n    }\r\n\r\n    .progress-container.support {\r\n        top: 154px;\r\n    }\r\n}\r\n\r\n@media(max-width:575.8px) {\r\n    .postmiansectbody__post h1 {\r\n        font-size: 38px;\r\n    }\r\n\r\n    .postmiansectbody__post h2 {\r\n        font-size: 36px;\r\n    }\r\n\r\n    .postmiansectbody__post h3 {\r\n        font-size: 32px;\r\n    }\r\n\r\n    .postmiansectbody__post h4 {\r\n        font-size: 21px;\r\n    }\r\n\r\n    .postmiansectbody__post h5,\r\n    .postmiansectbody__post h6 {\r\n        font-size: 16px;\r\n    }\r\n\r\n    .postmiansectbody__post ol {\r\n        padding-left: 0;\r\n\r\n        li {\r\n            padding-left: 0;\r\n        }\r\n    }\r\n\r\n    .mobsocbox p {\r\n        font-size: 14px;\r\n        margin-bottom: 8px;\r\n        text-align: center;\r\n    }\r\n\r\n    .mobsocbox ul li {\r\n        width: 44px;\r\n        height: 44px;\r\n        margin-bottom: 0;\r\n\r\n        a {\r\n            width: 42px;\r\n            height: 42px;\r\n        }\r\n    }\r\n\r\n    .contactauthor {\r\n        display: none;\r\n    }\r\n\r\n    .postmiansect__descr {\r\n        padding-right: 0;\r\n    }\r\n\r\n    .postauthor__wrap .postauthor {\r\n        max-width: 240px;\r\n    }\r\n\r\n    .tabletsocials {\r\n        padding-top: 25px;\r\n    }\r\n\r\n    .articlecontainer {\r\n        max-width: 100%;\r\n        padding-left: 19px !important;\r\n        padding-right: 19px !important;\r\n    }\r\n\r\n}\r\n\r\n\r\n.posttablewrapper table td {\r\n\r\n    ul,\r\n    ol {\r\n        padding-left: 18px;\r\n    }\r\n}\r\n\r\n.postmiansect__img {\r\n    display: flex;\r\n    align-items: center;\r\n}\r\n\r\n.blogsocials {\r\n    margin-top: 35px;\r\n}\r\n\r\n.postauthor__wrap {\r\n    display: flex;\r\n    flex-wrap: wrap;\r\n    align-items: center;\r\n\r\n    .postauthor {\r\n        width: 100%;\r\n        max-width: 290px;\r\n        flex: 0 0 290px;\r\n        margin-bottom: 15px;\r\n    }\r\n}\r\n\r\n.contactauthor a {\r\n    position: relative;\r\n    display: inline-block;\r\n    background: #C9FA3D;\r\n    padding: 12px 21px;\r\n    transition: 0.3s;\r\n    margin-bottom: 15px;\r\n\r\n    span {\r\n        color: #0F0F10;\r\n        letter-spacing: 0.05em;\r\n        font-weight: 700;\r\n        font-size: 16px;\r\n        line-height: 120%;\r\n        display: inline-block;\r\n    }\r\n\r\n    svg {\r\n        vertical-align: middle;\r\n        margin-top: -2px;\r\n\r\n        path {\r\n            stroke: #212121;\r\n        }\r\n    }\r\n\r\n    &:hover {\r\n        box-shadow: 0px 8px 20px rgba(67, 253, 130, 0.25), 0px 26px 50px #2f463a;\r\n    }\r\n}\r\n\r\n.service-faq.service-faq__hupd.faq_space,\r\n.service-faq.faq_space {\r\n    margin-top: 200px;\r\n    box-shadow: none;\r\n}\r\n\r\n.postnav {\r\n    width: 252px;\r\n    display: inline-block;\r\n    padding-left: 0;\r\n\r\n    p {\r\n        margin-bottom: 15px;\r\n        color: #0F0F10;\r\n        font-weight: 700;\r\n        font-size: 12px;\r\n        line-height: 150%;\r\n        margin-bottom: 15px;\r\n        text-align: left;\r\n    }\r\n\r\n    ul {\r\n        list-style-type: none;\r\n        padding: 0;\r\n        margin: 0 0 40px 0;\r\n        text-align: left;\r\n        position: relative;\r\n\r\n        &::after {\r\n            content: '';\r\n            display: inline-block;\r\n            width: 3px;\r\n            height: 100%;\r\n            background: #F6F6F6;\r\n            position: absolute;\r\n            left: 0;\r\n            top: 0;\r\n        }\r\n\r\n\r\n        li {\r\n            margin-bottom: 2px;\r\n\r\n            &:last-child {\r\n                margin-bottom: 0;\r\n            }\r\n\r\n            a {\r\n                color: #4B4B4B;\r\n                font-weight: 600;\r\n                font-size: 12px;\r\n                line-height: 150%;\r\n                position: relative;\r\n                padding: 8px 0 8px 19px;\r\n                display: block;\r\n\r\n                &.active {\r\n                    color: #0F0F10;\r\n                    font-weight: 700;\r\n\r\n                    &::after {\r\n                        content: '';\r\n                        width: 3px;\r\n                        height: 100%;\r\n                        position: absolute;\r\n                        left: 0;\r\n                        top: 0;\r\n                        background: #0F0F10;\r\n                        z-index: 2;\r\n                    }\r\n\r\n                    &:hover {\r\n                        color: #fff;\r\n                    }\r\n                }\r\n\r\n                &:hover {\r\n                    color: #fff;\r\n                    font-weight: 700;\r\n                    background: #333334;\r\n                }\r\n\r\n                &:focus, &:active {\r\n                    color: #fff;\r\n                    font-weight: 700;\r\n                    background: #333334;\r\n\r\n                    &::after {\r\n                        content: '';\r\n                        width: 3px;\r\n                        height: 100%;\r\n                        position: absolute;\r\n                        left: 0;\r\n                        top: 0;\r\n                        z-index: 2;\r\n                        background: linear-gradient(125.34deg,#CDFF7C 14.35%,#8CFFAC 54.63%,#93FFEB 101.27%);\r\n                    }\r\n                }\r\n            }\r\n        }\r\n    }\r\n}\r\n\r\n@media(min-width:1025px) {\r\n    .postbox-col:not(.w-100) {\r\n        .postbox {\r\n            position: relative;\r\n            height: 437px;\r\n            overflow: hidden;\r\n\r\n\r\n            .postbox__body-top {\r\n                padding: 16px 40px 0 40px;\r\n            }\r\n\r\n            .postbox__bottsect {\r\n                padding: 0 40px 30px 40px;\r\n            }\r\n\r\n            &:hover {\r\n                .postbox__body {\r\n                    height: 100%;\r\n                }\r\n\r\n                .descrtext {\r\n                    opacity: 1;\r\n                }\r\n            }\r\n        }\r\n\r\n        .postbox .postbox__body {\r\n            bottom: 0;\r\n            width: 100%;\r\n            height: calc(100% - 158px);\r\n            display: flex;\r\n            flex-direction: column;\r\n            justify-content: space-between;\r\n            transition: 0.5s;\r\n            position: absolute;\r\n        }\r\n\r\n        .postbox .descrtext {\r\n            font-size: 16px;\r\n            line-height: 140%;\r\n        }\r\n\r\n        .postbox .title {\r\n            margin-bottom: 0;\r\n            height: auto;\r\n        }\r\n\r\n        .postbox .descrtext {\r\n            opacity: 0;\r\n            transition: 0.5s;\r\n            padding-top: 10px;\r\n            display: -webkit-box;\r\n            -webkit-line-clamp: 6;\r\n            -webkit-box-orient: vertical;\r\n            overflow: hidden;\r\n        }\r\n\r\n        .postbox__body-top {\r\n            height: calc(100% - 60px);\r\n        }\r\n\r\n        .postbox .postbox__bottsect {\r\n            background: #fff;\r\n            position: relative;\r\n            z-index: 2;\r\n        }\r\n    }\r\n}\r\n\r\n@media(max-width:1024.8px) {\r\n    .postbox-col:not(.w-100) .postbox .descrtext {\r\n        display: none;\r\n    }\r\n}\r\n\r\n\r\n@media(max-width:1600.8px) {\r\n\r\n    .service-faq.service-faq__hupd.faq_space,\r\n    .service-faq.faq_space {\r\n        margin-top: 160px;\r\n    }\r\n}\r\n\r\n@media(max-width:1400.8px) {\r\n    .postbox-col:not(.w-100) .postbox .postbox__body-top {\r\n        padding: 10px 20px 0 20px;\r\n    }\r\n\r\n    .postbox-col:not(.w-100) .postbox .postbox__bottsect {\r\n        padding: 0 20px 10px 20px;\r\n    }\r\n\r\n    .postbox-col:not(.w-100) .postbox__body-top {\r\n        height: calc(100% - 40px);\r\n    }\r\n\r\n   \r\n\r\n}\r\n\r\n@media(max-width:991.8px) {\r\n    .descrtext {\r\n        display: none;\r\n    }\r\n\r\n    .service-faq.service-faq__hupd.faq_space,\r\n    .service-faq.faq_space {\r\n        margin-top: 100px;\r\n    }\r\n}\r\n\r\n@media(max-width:575.8px) {\r\n    .postbox-col:not(.w-100) .postbox .postbox__body-top {\r\n        padding: 16px 35px 0 35px;\r\n    }\r\n\r\n    .postbox-col:not(.w-100) .postbox .postbox__bottsect {\r\n        padding: 0 35px 20px 35px;\r\n    }\r\n\r\n    .postbox-col:not(.w-100) .postbox__body-top {\r\n        height: calc(100% - 50px);\r\n    }\r\n\r\n    .postbox-col:not(.w-100) .postbox .postbox__body {\r\n        height: calc(100% - 120px);\r\n    }\r\n\r\n    .postbox-col:not(.w-100) .postbox {\r\n        height: 330px;\r\n    }\r\n\r\n    .postbox .title {\r\n        -webkit-line-clamp: 3;\r\n    }\r\n\r\n    .postbox-col:not(.w-100) .postbox .descrtext {\r\n        -webkit-line-clamp: 4;\r\n    }\r\n\r\n    .postreadreview .postreadreview__link {\r\n        width: 100%;\r\n        max-width: 100%;\r\n    }\r\n\r\n    .postreadreview:before {\r\n        display: none;\r\n    }\r\n\r\n    .postreadreview h2 {\r\n        max-width: 100%;\r\n        padding-right: 100px;\r\n        position: relative;\r\n\r\n        &:before {\r\n            content: \"\";\r\n            display: block;\r\n            position: absolute;\r\n            background-repeat: no-repeat;\r\n            background-position: 0 0;\r\n            width: 100px;\r\n            height: 100px;\r\n            background-image: url(../images/new/subscribe-pic.png);\r\n            background-size: contain;\r\n            z-index: 2;\r\n            right: 0;\r\n            top: 50%;\r\n            transform: translateY(-50%);\r\n        }\r\n    }\r\n\r\n    .postbox-col:not(.w-100) .postbox__body-top {\r\n        height: auto;\r\n    }\r\n\r\n    .postbox-col:not(.w-100) .postbox .postbox__body,\r\n    .postbox-col:not(.w-100) .postbox {\r\n        height: auto;\r\n    }\r\n\r\n    .contactauthor {\r\n        margin: 0 auto;\r\n    }\r\n\r\n    .service-faq.service-faq__hupd.faq_space,\r\n    .service-faq.faq_space {\r\n        margin-top: 30px;\r\n    }\r\n\r\n}\r\n\r\n.postreadreview:not(.blackmob) {\r\n    background: transparent;\r\n}\r\n\r\n.postreadreview:not(.blackmob):after {\r\n    background-image: url(../images/homeupdate/without-noise.svg);\r\n    background-repeat: repeat;\r\n    background-color: #0A0A0B;\r\n    background-size: auto;\r\n}\r\n\r\n.articlestickyboxes {\r\n    position: sticky;\r\n    top: 160px;\r\n}\r\n\r\n.articlestickybox {\r\n    background: #fff;\r\n    border-radius: 0px 2px 2px 0px;\r\n    box-shadow: 0px 2px 12px 0px rgba(0, 0, 0, 0.10);\r\n    padding: 16px 16px 16px 39px;\r\n    display: inline-block;\r\n    width: 203px;\r\n    height: 110px;\r\n    transition: 0.5s;\r\n    overflow: hidden;\r\n    position: relative;\r\n    margin-bottom: 36px;\r\n    z-index: 3;\r\n\r\n    &.threepoint {\r\n        width: 260px;\r\n    }\r\n\r\n    .articlestickybox__info {\r\n        transition: 0.5s;\r\n        position: absolute;\r\n        opacity: 1;\r\n        top: 16px;\r\n        white-space: nowrap;\r\n\r\n        p {\r\n            margin-bottom: 8px;\r\n            color: #4B4B4B;\r\n            font-size: 14px;\r\n            font-weight: 500;\r\n            line-height: 160%;\r\n        }\r\n\r\n        .flex {\r\n            display: flex;\r\n            align-items: center;\r\n        }\r\n\r\n        ul {\r\n            list-style-type: none;\r\n            width: 100%;\r\n            max-width: calc(100% - 20px);\r\n            flex: 0 0 calc(100% - 20px);\r\n\r\n            li {\r\n                vertical-align: middle;\r\n                margin-right: 10px;\r\n                display: inline-flex;\r\n                align-items: center;\r\n                justify-content: center;\r\n                width: 48px;\r\n                height: 48px;\r\n                background: #D8D8D8;\r\n                border-radius: 50%;\r\n\r\n                &:hover {\r\n                    background: linear-gradient(125.34deg, #CDFF7C 14.35%, #8CFFAC 54.63%, #93FFEB 101.27%);\r\n                }\r\n\r\n                a {\r\n                    text-decoration: none;\r\n                    width: 44px;\r\n                    height: 44px;\r\n                    background: #fff;\r\n                    display: inline-flex;\r\n                    align-items: center;\r\n                    justify-content: center;\r\n                    border-radius: 50%;\r\n\r\n                    img {\r\n                        width: 20px;\r\n                    }\r\n                }\r\n            }\r\n        }\r\n\r\n        .arrow {\r\n            width: 100%;\r\n            max-width: 20px;\r\n            flex: 0 0 20px;\r\n            opacity: 0.5;\r\n            cursor: pointer;\r\n\r\n            img {\r\n                width: 100%;\r\n            }\r\n        }\r\n\r\n        .userlink {\r\n\r\n            a {\r\n                width: 100%;\r\n                height: 100%;\r\n                overflow: hidden;\r\n\r\n                img {\r\n                    width: 100%;\r\n                    height: 100%;\r\n                    object-fit: cover;\r\n                    object-position: 50% 50%;\r\n                }\r\n            }\r\n        }\r\n    }\r\n\r\n    .articlestickybox__open {\r\n        top: 40px;\r\n        transition: 0.5s;\r\n        position: absolute;\r\n        opacity: 0;\r\n        z-index: -1;\r\n\r\n        div {\r\n\r\n            vertical-align: middle;\r\n            display: inline-flex;\r\n            align-items: center;\r\n            justify-content: center;\r\n            width: 48px;\r\n            height: 48px;\r\n            background: #D8D8D8;\r\n            border-radius: 50%;\r\n\r\n            &:hover {\r\n                background: linear-gradient(125.34deg, #CDFF7C 14.35%, #8CFFAC 54.63%, #93FFEB 101.27%);\r\n            }\r\n\r\n            span {\r\n                text-decoration: none;\r\n                width: 44px;\r\n                height: 44px;\r\n                background: #fff;\r\n                display: inline-flex;\r\n                align-items: center;\r\n                justify-content: center;\r\n                border-radius: 50%;\r\n                cursor: pointer;\r\n\r\n                img {\r\n                    width: 20px;\r\n                }\r\n            }\r\n        }\r\n    }\r\n\r\n    &.hiddenelms {\r\n        width: 103px;\r\n        height: 80px;\r\n\r\n        .articlestickybox__info {\r\n            opacity: 0;\r\n            top: -40px;\r\n\r\n            &* {\r\n                white-space: nowrap;\r\n            }\r\n        }\r\n\r\n        .articlestickybox__open {\r\n            top: 16px;\r\n            opacity: 1;\r\n            z-index: 1;\r\n        }\r\n\r\n    }\r\n}\r\n\r\n// baners\r\n\r\n@font-face {\r\n    font-family: 'icomoon';\r\n    src: url('../fonts/icon/icomoon.eot?vzvn6t');\r\n    src: url('../fonts/icon/icomoon.eot?vzvn6t#iefix') format('embedded-opentype'),\r\n        url('../fonts/icon/icomoon.ttf?vzvn6t') format('truetype'),\r\n        url('../fonts/icon/icomoon.woff?vzvn6t') format('woff'),\r\n        url('../fonts/icon/icomoon.svg?vzvn6t#icomoon') format('svg');\r\n    font-weight: normal;\r\n    font-style: normal;\r\n    font-display: block;\r\n}\r\n\r\n[class^=\"icon-\"],\r\n[class*=\" icon-\"] {\r\n    font-family: 'icomoon' !important;\r\n    speak: never;\r\n    font-style: normal;\r\n    font-weight: normal;\r\n    font-variant: normal;\r\n    text-transform: none;\r\n    line-height: 1;\r\n\r\n    -webkit-font-smoothing: antialiased;\r\n    -moz-osx-font-smoothing: grayscale;\r\n}\r\n\r\n.icon-arrow-right2:before {\r\n    content: \"\\ea3c\";\r\n}\r\n\r\n.bnrbox {\r\n    display: flex;\r\n    align-items: center;\r\n    width: 100%;\r\n    height: 200px;\r\n    background: url('../images/new/background-bnr.png') no-repeat center / cover;\r\n    border-radius: 20px;\r\n    padding: 20px 10px 20px 40px;\r\n    overflow: hidden;\r\n    margin-bottom: 30px;\r\n\r\n    p {\r\n        width: 100%;\r\n        max-width: 517px;\r\n        flex: 0 0 517px;\r\n        color: #fff;\r\n        font-size: 36px;\r\n        font-weight: 700;\r\n        line-height: 110%;\r\n        background: linear-gradient(to right, white, white 50%, #8CFFAC 55%, #93FFEB);\r\n        -webkit-background-clip: text;\r\n        -webkit-text-fill-color: transparent;\r\n        background-size: 220% 100%;\r\n        background-position: 0%;\r\n        transition: background-position 0.42s ease;\r\n\r\n        span {\r\n            vertical-align: middle;\r\n            margin-top: -3px;\r\n            display: inline-block;\r\n        }\r\n    }\r\n\r\n    &:hover {\r\n        p {\r\n            background-position: 100%;\r\n        }\r\n\r\n        .bnrbox__img {\r\n            img {\r\n                transform: rotate(-30deg) scale(1.25);\r\n            }\r\n        }\r\n    }\r\n\r\n    .bnrbox__img {\r\n        width: 100%;\r\n        max-width: calc(100% - 517px);\r\n        flex: 0 0 calc(100% - 517px);\r\n        text-align: right;\r\n\r\n        img {\r\n            max-width: initial;\r\n            transition: 0.5s;\r\n            transform: rotate(0deg);\r\n            width: 240px;\r\n        }\r\n    }\r\n}\r\n\r\n\r\n\r\n@media(max-width:1700.8px) {\r\n    .bnrbox p {\r\n        max-width: 450px;\r\n        flex: 0 0 450px;\r\n        font-size: 30px;\r\n    }\r\n\r\n    .bnrbox .bnrbox__img {\r\n        max-width: calc(100% - 450px);\r\n        flex: 0 0 calc(100% - 450px);\r\n\r\n        img {\r\n            width: 180px;\r\n        }\r\n    }\r\n\r\n    .bnrbox {\r\n        height: 180px;\r\n    }\r\n   \r\n}\r\n\r\n@media(max-width:1600.8px) {\r\n    .bnrbox p {\r\n        max-width: 380px;\r\n        flex: 0 0 380px;\r\n        font-size: 25px;\r\n    }\r\n\r\n    .bnrbox .bnrbox__img {\r\n        max-width: calc(100% - 380px);\r\n        flex: 0 0 calc(100% - 380px);\r\n    }\r\n\r\n    .bnrbox {\r\n        height: 160px;\r\n    }\r\n\r\n   \r\n}\r\n\r\n@media(max-width:1440.8px) {\r\n    .bnrbox p {\r\n        max-width: 420px;\r\n        flex: 0 0 420px;\r\n        font-size: 26px;\r\n    }\r\n\r\n    .bnrbox .bnrbox__img {\r\n        max-width: calc(100% - 420px);\r\n        flex: 0 0 calc(100% - 420px);\r\n    }\r\n\r\n    .bnrbox .bnrbox__img {\r\n        text-align: right;\r\n    }\r\n}\r\n\r\n@media(max-width:1400.8px) {\r\n    .postnav {\r\n        width: 100%;\r\n        padding-left: 10px;\r\n    }\r\n\r\n   \r\n\r\n}\r\n\r\n@media(max-width:991.8px) {\r\n    .bnrbox p {\r\n        max-width: 380px;\r\n        flex: 0 0 380px;\r\n    }\r\n\r\n    .bnrbox .bnrbox__img {\r\n        max-width: calc(100% - 380px);\r\n        flex: 0 0 calc(100% - 380px);\r\n    }\r\n\r\n}\r\n\r\n@media(max-width:767.8px) {\r\n    .bnrbox {\r\n        height: 480px;\r\n        display: block;\r\n        padding: 24px;\r\n        position: relative;\r\n\r\n        p,\r\n        .bnrbox__img {\r\n            max-width: 100%;\r\n            flex: 0 0 100%;\r\n        }\r\n\r\n        p {\r\n            text-align: center;\r\n            font-size: 32px;\r\n        }\r\n\r\n        .bnrbox__img {\r\n            text-align: center;\r\n            position: absolute;\r\n            bottom: 0;\r\n            left: 0;\r\n            width: 100%;\r\n        }\r\n\r\n    }\r\n\r\n    .bnrbox .bnrbox__img img {\r\n        width: 260px;\r\n    }\r\n\r\n}\r\n\r\n@media(max-width:575.8px) {\r\n    .bnrbox {\r\n        height: 480px;\r\n        background: url(../images/new/background-bnrmob.png) no-repeat center/cover;\r\n    }\r\n\r\n    .bnrbox p {\r\n        position: relative;\r\n        z-index: 2;\r\n    }\r\n\r\n    .bnrbox p br {\r\n        display: none;\r\n    }\r\n\r\n    .bnrbox:hover .bnrbox__img img {\r\n        transform: rotate(0deg) scale(1);\r\n    }\r\n\r\n    .bnrbox .bnrbox__img img {\r\n        width: 240px;\r\n    }\r\n\r\n\r\n}\r\n\r\n@media(max-width:360.8px) {\r\n    .bnrbox {\r\n        height: 400px;\r\n\r\n        p {\r\n            font-size: 25px;\r\n        }\r\n    }\r\n}"
        }
    ]
}